fast_serve_api/__init__.py
fast_serve_api/fast_serve_api.py
fast_serve_api/py.typed
fast_serve_api/models/__init__.py
fast_serve_api/models/fast_serve_api_error_model.py
fast_serve_api/models/fast_serve_api_list_model.py
fast_serve_api/models/fast_serve_api_model.py
fast_serve_api-1.0.0.dist-info/METADATA
fast_serve_api-1.0.0.dist-info/WHEEL
fast_serve_api-1.0.0.dist-info/RECORD
