Metadata-Version: 2.4
Name: fast-serve-api
Version: 1.0.0
Summary: Transform services in default endpoints integrated by FastAPI and Pydantic.
Requires-Python: >=3.10.0
Requires-Dist: fastapi>=0.115.12
Requires-Dist: pydantic>=2.11.5
Provides-Extra: test
Requires-Dist: coverage>=7.0.0; extra == 'test'
Requires-Dist: httpx>=0.27.0; extra == 'test'
Requires-Dist: pytest-asyncio>=0.24.0; extra == 'test'
Requires-Dist: pytest>=8.0.0; extra == 'test'
